compas_ags/__init__.py
compas_ags/ags/__init__.py
compas_ags/ags/constraints.py
compas_ags/ags/core.py
compas_ags/ags/graphstatics.py
compas_ags/ags/loadpath.py
compas_ags/diagrams/__init__.py
compas_ags/diagrams/diagram.py
compas_ags/diagrams/forcediagram.py
compas_ags/diagrams/formdiagram.py
compas_ags/diagrams/formgraph.py
compas_ags/exceptions/__init__.py
compas_ags/exceptions/errorhandler.py
compas_ags/viewer/__init__.py
compas_ags/viewer/viewer.py
compas_ags-1.3.3.dist-info/AUTHORS.md
compas_ags-1.3.3.dist-info/LICENSE
compas_ags-1.3.3.dist-info/METADATA
compas_ags-1.3.3.dist-info/WHEEL
compas_ags-1.3.3.dist-info/top_level.txt
compas_ags-1.3.3.dist-info/RECORD
