Metadata-Version: 2.1
Name: compas_ags
Version: 1.3.3
Summary: COMPAS package for Computational Graphic Statics
Author-email: tom van mele <tom.v.mele@gmail.com>, Vedad Alic <vedad.alic@outlook.com>, Andrew Liew <a.liew@sheffield.ac.uk>
License: MIT License
Project-URL: Homepage, https://compas-dev.github.io/compas_ags
Project-URL: Documentation, https://compas-dev.github.io/compas_ags
Project-URL: Repository, https://github.com/compas-dev/compas_ags.git
Project-URL: Changelog, https://github.com/compas-dev/compas_ags/blob/main/CHANGELOG.md
Keywords: graphic statics,2D structures
Classifier: Development Status :: 4 - Beta
Classifier: Topic :: Scientific/Engineering
Classifier: Programming Language :: Python
Classifier: Programming Language :: Python :: 3
Classifier: Programming Language :: Python :: 3.9
Classifier: Programming Language :: Python :: 3.10
Classifier: Programming Language :: Python :: 3.11
Requires-Python: >=3.9
License-File: LICENSE
License-File: AUTHORS.md
Requires-Dist: compas
Requires-Dist: sympy
Provides-Extra: dev
Requires-Dist: attrs>=17.4; extra == "dev"
Requires-Dist: black>=22.12.0; extra == "dev"
Requires-Dist: bump-my-version; extra == "dev"
Requires-Dist: compas_invocations2; extra == "dev"
Requires-Dist: compas_notebook; extra == "dev"
Requires-Dist: compas_viewer; extra == "dev"
Requires-Dist: invoke>=0.14; extra == "dev"
Requires-Dist: ruff; extra == "dev"
Requires-Dist: sphinx_compas2_theme; extra == "dev"
Requires-Dist: twine; extra == "dev"
Requires-Dist: wheel; extra == "dev"
